<annotation>
	<folder>path</folder>
	<filename>new_data31.jpeg</filename>
	<path>D:\path\new_data31.jpeg</path>
	<source>
		<database>Unknown</database>
	</source>
	<size>
		<width>958</width>
		<height>1280</height>
		<depth>3</depth>
	</size>
	<segmented>0</segmented>
	<object>
		<name>rouille</name>
		<pose>Unspecified</pose>
		<truncated>1</truncated>
		<difficult>0</difficult>
		<bndbox>
			<xmin>314</xmin>
			<ymin>2</ymin>
			<xmax>958</xmax>
			<ymax>467</ymax>
		</bndbox>
	</object>
	<object>
		<name>rouille</name>
		<pose>Unspecified</pose>
		<truncated>1</truncated>
		<difficult>0</difficult>
		<bndbox>
			<xmin>613</xmin>
			<ymin>506</ymin>
			<xmax>958</xmax>
			<ymax>869</ymax>
		</bndbox>
	</object>
	<object>
		<name>rouille</name>
		<pose>Unspecified</pose>
		<truncated>0</truncated>
		<difficult>0</difficult>
		<bndbox>
			<xmin>341</xmin>
			<ymin>963</ymin>
			<xmax>529</xmax>
			<ymax>1206</ymax>
		</bndbox>
	</object>
	<object>
		<name>rouille</name>
		<pose>Unspecified</pose>
		<truncated>0</truncated>
		<difficult>0</difficult>
		<bndbox>
			<xmin>316</xmin>
			<ymin>444</ymin>
			<xmax>536</xmax>
			<ymax>1031</ymax>
		</bndbox>
	</object>
</annotation>
