<annotation>
	<folder>path</folder>
	<filename>new_data119.jpeg</filename>
	<path>D:\path\new_data119.jpeg</path>
	<source>
		<database>Unknown</database>
	</source>
	<size>
		<width>960</width>
		<height>1280</height>
		<depth>3</depth>
	</size>
	<segmented>0</segmented>
	<object>
		<name>polystigma</name>
		<pose>Unspecified</pose>
		<truncated>1</truncated>
		<difficult>0</difficult>
		<bndbox>
			<xmin>1</xmin>
			<ymin>367</ymin>
			<xmax>226</xmax>
			<ymax>753</ymax>
		</bndbox>
	</object>
	<object>
		<name>polystigma</name>
		<pose>Unspecified</pose>
		<truncated>0</truncated>
		<difficult>0</difficult>
		<bndbox>
			<xmin>390</xmin>
			<ymin>500</ymin>
			<xmax>518</xmax>
			<ymax>803</ymax>
		</bndbox>
	</object>
	<object>
		<name>polystigma</name>
		<pose>Unspecified</pose>
		<truncated>0</truncated>
		<difficult>0</difficult>
		<bndbox>
			<xmin>611</xmin>
			<ymin>530</ymin>
			<xmax>751</xmax>
			<ymax>842</ymax>
		</bndbox>
	</object>
	<object>
		<name>polystigma</name>
		<pose>Unspecified</pose>
		<truncated>0</truncated>
		<difficult>0</difficult>
		<bndbox>
			<xmin>828</xmin>
			<ymin>548</ymin>
			<xmax>953</xmax>
			<ymax>938</ymax>
		</bndbox>
	</object>
	<object>
		<name>polystigma</name>
		<pose>Unspecified</pose>
		<truncated>0</truncated>
		<difficult>0</difficult>
		<bndbox>
			<xmin>563</xmin>
			<ymin>396</ymin>
			<xmax>651</xmax>
			<ymax>604</ymax>
		</bndbox>
	</object>
	<object>
		<name>polystigma</name>
		<pose>Unspecified</pose>
		<truncated>0</truncated>
		<difficult>0</difficult>
		<bndbox>
			<xmin>715</xmin>
			<ymin>271</ymin>
			<xmax>860</xmax>
			<ymax>565</ymax>
		</bndbox>
	</object>
</annotation>
