<annotation>
	<folder>path</folder>
	<filename>new_data486.jpeg</filename>
	<path>D:\path\new_data486.jpeg</path>
	<source>
		<database>Unknown</database>
	</source>
	<size>
		<width>960</width>
		<height>1280</height>
		<depth>3</depth>
	</size>
	<segmented>0</segmented>
	<object>
		<name>acariens</name>
		<pose>Unspecified</pose>
		<truncated>1</truncated>
		<difficult>0</difficult>
		<bndbox>
			<xmin>407</xmin>
			<ymin>677</ymin>
			<xmax>657</xmax>
			<ymax>1280</ymax>
		</bndbox>
	</object>
	<object>
		<name>acariens</name>
		<pose>Unspecified</pose>
		<truncated>1</truncated>
		<difficult>0</difficult>
		<bndbox>
			<xmin>1</xmin>
			<ymin>391</ymin>
			<xmax>409</xmax>
			<ymax>685</ymax>
		</bndbox>
	</object>
	<object>
		<name>acariens</name>
		<pose>Unspecified</pose>
		<truncated>1</truncated>
		<difficult>0</difficult>
		<bndbox>
			<xmin>575</xmin>
			<ymin>84</ymin>
			<xmax>960</xmax>
			<ymax>515</ymax>
		</bndbox>
	</object>
</annotation>
