<annotation>
	<folder>path</folder>
	<filename>new_data152.jpeg</filename>
	<path>D:\path\new_data152.jpeg</path>
	<source>
		<database>Unknown</database>
	</source>
	<size>
		<width>958</width>
		<height>1280</height>
		<depth>3</depth>
	</size>
	<segmented>0</segmented>
	<object>
		<name>polystigma</name>
		<pose>Unspecified</pose>
		<truncated>0</truncated>
		<difficult>0</difficult>
		<bndbox>
			<xmin>363</xmin>
			<ymin>742</ymin>
			<xmax>423</xmax>
			<ymax>823</ymax>
		</bndbox>
	</object>
	<object>
		<name>polystigma</name>
		<pose>Unspecified</pose>
		<truncated>0</truncated>
		<difficult>0</difficult>
		<bndbox>
			<xmin>354</xmin>
			<ymin>453</ymin>
			<xmax>416</xmax>
			<ymax>602</ymax>
		</bndbox>
	</object>
	<object>
		<name>polystigma</name>
		<pose>Unspecified</pose>
		<truncated>0</truncated>
		<difficult>0</difficult>
		<bndbox>
			<xmin>244</xmin>
			<ymin>731</ymin>
			<xmax>367</xmax>
			<ymax>784</ymax>
		</bndbox>
	</object>
	<object>
		<name>polystigma</name>
		<pose>Unspecified</pose>
		<truncated>0</truncated>
		<difficult>0</difficult>
		<bndbox>
			<xmin>12</xmin>
			<ymin>730</ymin>
			<xmax>58</xmax>
			<ymax>804</ymax>
		</bndbox>
	</object>
	<object>
		<name>polystigma</name>
		<pose>Unspecified</pose>
		<truncated>0</truncated>
		<difficult>0</difficult>
		<bndbox>
			<xmin>440</xmin>
			<ymin>571</ymin>
			<xmax>527</xmax>
			<ymax>631</ymax>
		</bndbox>
	</object>
</annotation>
