<annotation>
	<folder>path</folder>
	<filename>new_data147.jpeg</filename>
	<path>D:\path\new_data147.jpeg</path>
	<source>
		<database>Unknown</database>
	</source>
	<size>
		<width>960</width>
		<height>1280</height>
		<depth>3</depth>
	</size>
	<segmented>0</segmented>
	<object>
		<name>polystigma</name>
		<pose>Unspecified</pose>
		<truncated>0</truncated>
		<difficult>0</difficult>
		<bndbox>
			<xmin>369</xmin>
			<ymin>642</ymin>
			<xmax>579</xmax>
			<ymax>1257</ymax>
		</bndbox>
	</object>
	<object>
		<name>polystigma</name>
		<pose>Unspecified</pose>
		<truncated>0</truncated>
		<difficult>0</difficult>
		<bndbox>
			<xmin>224</xmin>
			<ymin>2</ymin>
			<xmax>502</xmax>
			<ymax>354</ymax>
		</bndbox>
	</object>
</annotation>
